[
  {
    "id": 1,
    "name": "Sacred Games",
    "type": "Web Series",
    "seasons": 2,
    "rating": 8.5,
    "characters": [
      "Ganesh Gaitonde",
      "Sartaj Singh",
      "Kukoo",
      "Anjali Mathur"
    ],
    "poster": "https://m.media-amazon.com/images/M/MV5BMTE3MGI4YzQtZWYxZS00NjJjLTkxNmEtOTAyZjgxNzM1ZDY1XkEyXkFqcGdeQXVyMTExNDQ2MTI@._V1_.jpg"
  },
  {
    "id": 2,
    "name": "Mirzapur",
    "type": "Web Series",
    "seasons": 3,
    "rating": 8.4,
    "characters": [
      "Kaleen Bhaiya",
      "Guddu Pandit",
      "Bablu Pandit",
      "Munna Tripathi"
    ],
    "poster": "https://m.media-amazon.com/images/M/MV5BYmQ1ZWM0MGQtYzFhMC00MjQ4LWJkNzMtNmYzY2Q3ZjZmYjQ3XkEyXkFqcGdeQXVyMTExNDQ2MTI@._V1_.jpg"
  },
  {
    "id": 3,
    "name": "The Family Man",
    "type": "Web Series",
    "seasons": 2,
    "rating": 8.7,
    "characters": [
      "Srikant Tiwari",
      "Suchitra Tiwari",
      "JK Talpade",
      "Raji"
    ],
    "poster": "https://m.media-amazon.com/images/M/MV5BODU4MzQzNjEtNmY2OC00Y2UxLTk2YzMtOTQ4YjYzODg5ZDU2XkEyXkFqcGdeQXVyMTExNDQ2MTI@._V1_.jpg"
  },
  {
    "id": 4,
    "name": "Scam 1992",
    "type": "Web Series",
    "seasons": 1,
    "rating": 9.3,
    "characters": [
      "Harshad Mehta",
      "Ashwin Mehta",
      "Suchitra Dalal",
      "Manu Mundra"
    ],
    "poster": "https://m.media-amazon.com/images/M/MV5BZjhkOTYxMzQtODQ1My00YWE3LTg3YjAtNGQ2Y2YyYjJkZjk3XkEyXkFqcGdeQXVyMTExNDQ2MTI@._V1_.jpg"
  },
  {
    "id": 5,
    "name": "Pathaan",
    "type": "Movie",
    "seasons": 0,
    "rating": 6.6,
    "characters": [
      "Pathaan",
      "Rubina",
      "Jim",
      "Nandini"
    ],
    "poster": "https://m.media-amazon.com/images/M/MV5BYjUzODUxNjAtY2Q3Zi00Y2Q1LWE4MjktN2Q0M2Q5ZTZlN2NjXkEyXkFqcGdeQXVyMTUzMTg2ODkz._V1_.jpg"
  },
  {
    "id": 6,
    "name": "Jawan",
    "type": "Movie",
    "seasons": 0,
    "rating": 7.0,
    "characters": [
      "Azad",
      "Vikram Rathore",
      "Narmada",
      "Kalee"
    ],
    "poster": "https://m.media-amazon.com/images/M/MV5BZDQ0NzI4MWQtZGY5ZS00YjlhLWIyOWEtNzJhMzJhYzY3ZDU1XkEyXkFqcGdeQXVyMTUzMTg2ODkz._V1_.jpg"
  },
  {
    "id": 7,
    "name": "3 Idiots",
    "type": "Movie",
    "seasons": 0,
    "rating": 8.4,
    "characters": [
      "Rancho",
      "Farhan",
      "Raju",
      "Virus"
    ],
    "poster": "https://m.media-amazon.com/images/M/MV5BMjIxMjgxNzM2NF5BMl5BanBnXkFtZTcwOTkzOTQ3Mg@@._V1_.jpg"
  },
  {
    "id": 8,
    "name": "Dangal",
    "type": "Movie",
    "seasons": 0,
    "rating": 8.3,
    "characters": [
      "Mahavir Singh Phogat",
      "Geeta Phogat",
      "Babita Phogat",
      "Omkar"
    ],
    "poster": "https://m.media-amazon.com/images/M/MV5BMTc5Nzc4NzYzNF5BMl5BanBnXkFtZTgwODg4NjU3OTE@._V1_.jpg"
  },
  {
    "id": 9,
    "name": "Drishyam",
    "type": "Movie",
    "seasons": 0,
    "rating": 8.2,
    "characters": [
      "Vijay Salgaonkar",
      "Nandini",
      "IG Meera Deshmukh",
      "Anju"
    ],
    "poster": "https://m.media-amazon.com/images/M/MV5BYmJhZDM3OTMtYjYzZS00ZmQ5LWFjNDctODI0MjM1NzY4NzQyXkEyXkFqcGdeQXVyMTExNDQ2MTI@._V1_.jpg"
  },
  {
    "id": 10,
    "name": "War",
    "type": "Movie",
    "seasons": 0,
    "rating": 6.5,
    "characters": [
      "Kabir",
      "Khalid",
      "Naina",
      "Colonel Luthra"
    ],
    "poster": "https://m.media-amazon.com/images/M/MV5BODI4NDcxNjktNzYxYi00ZDI1LTljNjUtYzY0ZDFkMzFhZTBjXkEyXkFqcGdeQXVyMTExNDQ2MTI@._V1_.jpg"
  }
]
